{"products":[{"id":1,"price":88225,"description":"Practical Frozen Soap","name":"Chair","imageUrl":"https://cdn.fakercloud.com/avatars/oktayelipek_128.jpg","status":true,"category":"Shoes"},{"id":2,"price":10912,"description":"Intelligent Steel Shoes","name":"Hat","imageUrl":"https://cdn.fakercloud.com/avatars/scips_128.jpg","status":false,"category":"Kids"},{"id":3,"price":94987,"description":"Handcrafted Steel Ball","name":"Tuna","imageUrl":"https://cdn.fakercloud.com/avatars/gabrielrosser_128.jpg","status":false,"category":"Baby"},{"id":4,"price":68332,"description":"Handcrafted Frozen Sausages","name":"Chicken","imageUrl":"https://cdn.fakercloud.com/avatars/emsgulam_128.jpg","status":true,"category":"Clothing"},{"id":5,"price":66840,"description":"Awesome Plastic Chips","name":"Shoes","imageUrl":"https://cdn.fakercloud.com/avatars/gipsy_raf_128.jpg","status":false,"category":"Electronics"},{"id":6,"price":95843,"description":"Small Frozen Sausages","name":"Salad","imageUrl":"https://cdn.fakercloud.com/avatars/mutu_krish_128.jpg","status":false,"category":"Toys"},{"id":7,"price":81294,"description":"Small Granite Computer","name":"Bike","imageUrl":"https://cdn.fakercloud.com/avatars/hellofeverrrr_128.jpg","status":false,"category":"Industrial"},{"id":8,"price":81050,"description":"Handcrafted Granite Cheese","name":"Towels","imageUrl":"https://cdn.fakercloud.com/avatars/agromov_128.jpg","status":true,"category":"Automotive"},{"id":9,"price":79455,"description":"Unbranded Soft Chicken","name":"Cheese","imageUrl":"https://cdn.fakercloud.com/avatars/dss49_128.jpg","status":false,"category":"Books"},{"id":10,"price":61163,"description":"Small Granite Pants","name":"Soap","imageUrl":"https://cdn.fakercloud.com/avatars/serefka_128.jpg","status":true,"category":"Kids"},{"id":11,"price":9766,"description":"Generic Wooden Hat","name":"Computer","imageUrl":"https://cdn.fakercloud.com/avatars/uxward_128.jpg","status":true,"category":"Toys"},{"id":12,"price":7820,"description":"Sleek Cotton Bike","name":"Soap","imageUrl":"https://cdn.fakercloud.com/avatars/borantula_128.jpg","status":true,"category":"Toys"},{"id":13,"price":87907,"description":"Intelligent Rubber Mouse","name":"Towels","imageUrl":"https://cdn.fakercloud.com/avatars/chrisstumph_128.jpg","status":true,"category":"Jewelery"},{"id":14,"price":20645,"description":"Practical Frozen Shoes","name":"Computer","imageUrl":"https://cdn.fakercloud.com/avatars/newbrushes_128.jpg","status":false,"category":"Books"},{"id":15,"price":2689,"description":"Refined Concrete Sausages","name":"Chicken","imageUrl":"https://cdn.fakercloud.com/avatars/jackiesaik_128.jpg","status":true,"category":"Jewelery"},{"id":16,"price":87826,"description":"Rustic Wooden Fish","name":"Tuna","imageUrl":"https://cdn.fakercloud.com/avatars/aio____128.jpg","status":false,"category":"Sports"},{"id":17,"price":59900,"description":"Rustic Steel Pizza","name":"Gloves","imageUrl":"https://cdn.fakercloud.com/avatars/increase_128.jpg","status":false,"category":"Garden"},{"id":18,"price":95567,"description":"Handmade Soft Bike","name":"Bacon","imageUrl":"https://cdn.fakercloud.com/avatars/fiterik_128.jpg","status":false,"category":"Sports"},{"id":19,"price":39016,"description":"Intelligent Rubber Chicken","name":"Pants","imageUrl":"https://cdn.fakercloud.com/avatars/trueblood_33_128.jpg","status":true,"category":"Games"},{"id":20,"price":88591,"description":"Handcrafted Steel Salad","name":"Chair","imageUrl":"https://cdn.fakercloud.com/avatars/kirangopal_128.jpg","status":true,"category":"Grocery"}]}
